reskyblock-0.2.8.dist-info/METADATA
reskyblock-0.2.8.dist-info/WHEEL
reskyblock-0.2.8.dist-info/entry_points.txt
reskyblock-0.2.8.dist-info/licenses/LICENSE
reskyblock/__init__.py
reskyblock/__main__.py
reskyblock/client.py
reskyblock/http/__init__.py
reskyblock/http/http_adapter.py
reskyblock/models/__init__.py
reskyblock/models/auctions.py
reskyblock/models/auctions_ended.py
reskyblock/models/bazaar.py
reskyblock/nbt/__init__.py
reskyblock/nbt/decoder.py
reskyblock/py.typed
reskyblock/serialization/__init__.py
reskyblock/serialization/json.py
reskyblock/urls.py
reskyblock-0.2.8.dist-info/RECORD
