Metadata-Version: 2.1
Name: reskyblock
Version: 0.2.8
Summary: Python API wrapper for Hypixel SkyBlock
Author-Email: ch-iv <alicesummer38@gmail.com>
License: MIT
Requires-Python: >=3.12
Requires-Dist: httpx>=0.26.0
Requires-Dist: msgspec>=0.18.6
Requires-Dist: nbt>=1.5.1
Requires-Dist: nbt2dict>=0.1.0
